steampak/__init__.py
steampak/cli.py
steampak/exceptions.py
steampak/libsteam/__init__.py
steampak/libsteam/exceptions.py
steampak/libsteam/resources/__init__.py
steampak/libsteam/resources/_versions.py
steampak/libsteam/resources/_wrapper.py
steampak/libsteam/resources/apps.py
steampak/libsteam/resources/base.py
steampak/libsteam/resources/friends.py
steampak/libsteam/resources/groups.py
steampak/libsteam/resources/main.py
steampak/libsteam/resources/overlay.py
steampak/libsteam/resources/screenshots.py
steampak/libsteam/resources/stats.py
steampak/libsteam/resources/user.py
steampak/libsteam/resources/utils.py
steampak/webapi/__init__.py
steampak/webapi/exceptions.py
steampak/webapi/settings.py
steampak/webapi/utils.py
steampak/webapi/resources/__init__.py
steampak/webapi/resources/apps.py
steampak/webapi/resources/market.py
steampak/webapi/resources/user.py
steampak-0.7.0.dist-info/DESCRIPTION.rst
steampak-0.7.0.dist-info/METADATA
steampak-0.7.0.dist-info/RECORD
steampak-0.7.0.dist-info/WHEEL
steampak-0.7.0.dist-info/entry_points.txt
steampak-0.7.0.dist-info/metadata.json
steampak-0.7.0.dist-info/top_level.txt
