Metadata-Version: 2.0
Name: steampak
Version: 0.7.0
Summary: Nicely packed tools to work with Steam APIs
Home-page: https://github.com/idlesign/steampak
Author: Igor `idle sign` Starikov
Author-email: idlesign@yandex.ru
License: BSD 3-Clause License
Platform: UNKNOWN
Classifier: Development Status :: 4 - Beta
Classifier: Operating System :: OS Independent
Classifier: Programming Language :: Python
Classifier: Programming Language :: Python :: 3
Classifier: Programming Language :: Python :: 3.6
Classifier: License :: OSI Approved :: BSD License
Provides-Extra: extra
Provides-Extra: webapi
Requires-Dist: ctyped (>=0.7.0)
Provides-Extra: extra
Requires-Dist: requests; extra == 'extra'
Requires-Dist: bs4; extra == 'extra'
Requires-Dist: click; extra == 'extra'
Provides-Extra: webapi
Requires-Dist: requests; extra == 'webapi'
Requires-Dist: bs4; extra == 'webapi'
